README.rst
setup.py
virtstrap_custom_script/__init__.py
virtstrap_custom_script/plugin.py
virtstrap_custom_script.egg-info/PKG-INFO
virtstrap_custom_script.egg-info/SOURCES.txt
virtstrap_custom_script.egg-info/dependency_links.txt
virtstrap_custom_script.egg-info/entry_points.txt
virtstrap_custom_script.egg-info/not-zip-safe
virtstrap_custom_script.egg-info/requires.txt
virtstrap_custom_script.egg-info/top_level.txt