Metadata-Version: 1.0
Name: virtstrap-custom-script
Version: 0.0.1
Summary: A virtstrap plugin that runs a custom script on install
Home-page: http://github.com/ravenac95/virtstrap-custom-script
Author: Reuven V. Gonzales
Author-email: reuven@tobetter.us
License: MIT
Keywords: virtstrap ruby bundler virtualenv pip
Platform: UNKNOWN
